pyhpoapi/__init__.py
pyhpoapi/config.py
pyhpoapi/helpers.py
pyhpoapi/main.py
pyhpoapi/models.py
pyhpoapi/server.py
pyhpoapi/resources/logo.png
pyhpoapi/routers/__init__.py
pyhpoapi/routers/annotations.py
pyhpoapi/routers/term.py
pyhpoapi/routers/terms.py
pyhpoapi-2.0.0.dist-info/LICENSE
pyhpoapi-2.0.0.dist-info/METADATA
pyhpoapi-2.0.0.dist-info/WHEEL
pyhpoapi-2.0.0.dist-info/top_level.txt
pyhpoapi-2.0.0.dist-info/RECORD
