Metadata-Version: 2.1
Name: pyhpoapi
Version: 2.0.0
Summary: A REST API for the HPO ontology using PyHPO
Author-email: Jonas Marcello <jonas.marcello@esbme.com>
License: MIT License
Keywords: HPO,REST-API,Bioinformatics,Ontology,Phenotype
Platform: UNKNOWN
Classifier: Development Status :: 5 - Production/Stable
Classifier: Intended Audience :: Developers
Classifier: Intended Audience :: Healthcare Industry
Classifier: Intended Audience :: Science/Research
Classifier: Intended Audience :: System Administrators
Classifier: License :: OSI Approved :: MIT License
Classifier: Operating System :: OS Independent
Classifier: Programming Language :: Python :: 3.7
Classifier: Programming Language :: Python :: 3.8
Classifier: Programming Language :: Python :: 3.9
Classifier: Programming Language :: Python :: 3.10
Classifier: Programming Language :: Python :: 3.11
Classifier: Programming Language :: Python :: Implementation :: CPython
Classifier: Programming Language :: Python :: Implementation :: PyPy
Classifier: Topic :: Scientific/Engineering :: Bio-Informatics
Classifier: Topic :: Scientific/Engineering :: Medical Science Apps.
Classifier: Topic :: Software Development :: Libraries :: Python Modules
Classifier: Topic :: Internet :: WWW/HTTP :: Dynamic Content
Classifier: Topic :: Internet :: WWW/HTTP :: HTTP Servers
Classifier: Topic :: Internet :: WWW/HTTP :: WSGI :: Application
Requires-Python: >=3.7
License-File: LICENSE
Requires-Dist: pydantic (>=2)
Requires-Dist: scipy
Requires-Dist: pyhpo (>=3.2)
Requires-Dist: fastapi (>=0.100)
Requires-Dist: uvicorn
Requires-Dist: aiofiles
